wheelie/__init__.py
wheelie/_version.py
wheelie/exporter.py
wheelie/setup.py
wheelie/wheelie.py
wheelie-0.1.1.dist-info/METADATA
wheelie-0.1.1.dist-info/RECORD
wheelie-0.1.1.dist-info/WHEEL
wheelie-0.1.1.dist-info/entry_points.txt
wheelie-0.1.1.dist-info/top_level.txt
